ImageToAscii/GrayscaleToAscii.py
ImageToAscii/ImageToAscii.py
ImageToAscii/ImageToGrayscale.py
ImageToAscii/__init__.py
ImageToAscii-1.0.5a0.dist-info/METADATA
ImageToAscii-1.0.5a0.dist-info/WHEEL
ImageToAscii-1.0.5a0.dist-info/top_level.txt
ImageToAscii-1.0.5a0.dist-info/RECORD
